{"images": [{"file_name": "target_2023_04_28_14_22_05_861295.jpg", "height": 1480, "width": 720, "id": 1}, {"file_name": "target_2023_04_28_14_23_52_829036.jpg", "height": 1480, "width": 720, "id": 2}, {"file_name": "target_2023_04_28_14_23_23_625893.jpg", "height": 1480, "width": 720, "id": 3}, {"file_name": "target_2023_04_28_14_24_05_164660.jpg", "height": 1480, "width": 720, "id": 4}, {"file_name": "target_2023_04_28_14_22_29_365276.jpg", "height": 1480, "width": 720, "id": 5}, {"file_name": "target_2023_04_28_14_27_36_877739.jpg", "height": 1480, "width": 720, "id": 6}, {"file_name": "target_2023_04_28_14_26_30_316300.jpg", "height": 1480, "width": 720, "id": 7}, {"file_name": "target_2023_04_28_14_26_39_066753.jpg", "height": 1480, "width": 720, "id": 8}, {"file_name": "target_2023_04_28_14_25_36_155348.jpg", "height": 1480, "width": 720, "id": 9}, {"file_name": "target_2023_04_28_14_25_14_084813.jpg", "height": 1480, "width": 720, "id": 10}, {"file_name": "target_2023_04_28_14_29_01_987030.jpg", "height": 1480, "width": 720, "id": 11}, {"file_name": "target_2023_04_28_14_30_51_859837.jpg", "height": 1480, "width": 720, "id": 12}, {"file_name": "target_2023_04_28_14_30_31_437370.jpg", "height": 1480, "width": 720, "id": 13}, {"file_name": "target_2023_04_28_14_30_14_153937.jpg", "height": 1480, "width": 720, "id": 14}, {"file_name": "target_2023_04_28_14_29_14_616748.jpg", "height": 1480, "width": 720, "id": 15}, {"file_name": "target_2023_04_28_14_33_18_801723.jpg", "height": 1480, "width": 720, "id": 16}, {"file_name": "target_2023_04_28_14_33_40_890631.jpg", "height": 1480, "width": 720, "id": 17}, {"file_name": "target_2023_04_28_14_34_03_558390.jpg", "height": 1480, "width": 720, "id": 18}, {"file_name": "target_2023_04_28_14_34_33_440519.jpg", "height": 1480, "width": 720, "id": 19}, {"file_name": "target_2023_04_28_14_33_25_863558.jpg", "height": 1480, "width": 720, "id": 20}, {"file_name": "target_2023_04_28_14_35_25_171892.jpg", "height": 1480, "width": 720, "id": 21}, {"file_name": "target_2023_04_28_14_37_28_341544.jpg", "height": 1480, "width": 720, "id": 22}, {"file_name": "target_2023_04_28_14_37_44_333176.jpg", "height": 1480, "width": 720, "id": 23}, {"file_name": "target_2023_04_28_14_38_01_105093.jpg", "height": 1480, "width": 720, "id": 24}, {"file_name": "target_2023_04_28_14_35_31_784927.jpg", "height": 1480, "width": 720, "id": 25}, {"file_name": "target_2023_04_28_14_39_36_444403.jpg", "height": 1480, "width": 720, "id": 26}, {"file_name": "target_2023_04_28_14_39_24_293416.jpg", "height": 1480, "width": 720, "id": 27}, {"file_name": "target_2023_04_28_14_39_16_009422.jpg", "height": 1480, "width": 720, "id": 28}, {"file_name": "target_2023_04_28_14_38_46_595502.jpg", "height": 1480, "width": 720, "id": 29}, {"file_name": "target_2023_04_28_14_38_42_133833.jpg", "height": 1480, "width": 720, "id": 30}, {"file_name": "target_2023_04_28_14_45_53_001135.jpg", "height": 1480, "width": 720, "id": 31}, {"file_name": "target_2023_04_28_14_45_47_200048.jpg", "height": 1480, "width": 720, "id": 32}, {"file_name": "target_2023_04_28_14_46_49_116913.jpg", "height": 1480, "width": 720, "id": 33}, {"file_name": "target_2023_04_28_14_42_25_277914.jpg", "height": 1480, "width": 720, "id": 34}, {"file_name": "target_2023_04_28_14_46_31_316525.jpg", "height": 1480, "width": 720, "id": 35}], "type": "instances", "annotations": [{"area": 101386, "iscrowd": 0, "bbox": [158, 593, 326, 311], "category_id": 1, "ignore": 0, "segmentation": [], "image_id": 1, "id": 1}, {"area": 52056, "iscrowd": 0, "bbox": [113, 885, 216, 241], "category_id": 1, "ignore": 0, "segmentation": [], "image_id": 2, "id": 2}, {"area": 117294, "iscrowd": 0, "bbox": [190, 560, 346, 339], "category_id": 1, "ignore": 0, "segmentation": [], "image_id": 3, "id": 3}, {"area": 50451, "iscrowd": 0, "bbox": [188, 548, 201, 251], "category_id": 1, "ignore": 0, "segmentation": [], "image_id": 4, "id": 4}, {"area": 109716, "iscrowd": 0, "bbox": [138, 573, 446, 246], "category_id": 1, "ignore": 0, "segmentation": [], "image_id": 5, "id": 5}, {"area": 27492, "iscrowd": 0, "bbox": [243, 580, 158, 174], "category_id": 2, "ignore": 0, "segmentation": [], "image_id": 6, "id": 6}, {"area": 282204, "iscrowd": 0, "bbox": [63, 523, 603, 468], "category_id": 2, "ignore": 0, "segmentation": [], "image_id": 7, "id": 7}, {"area": 179858, "iscrowd": 0, "bbox": [83, 598, 406, 443], "category_id": 2, "ignore": 0, "segmentation": [], "image_id": 8, "id": 8}, {"area": 195822, "iscrowd": 0, "bbox": [153, 575, 473, 414], "category_id": 2, "ignore": 0, "segmentation": [], "image_id": 9, "id": 9}, {"area": 108466, "iscrowd": 0, "bbox": [105, 555, 386, 281], "category_id": 2, "ignore": 0, "segmentation": [], "image_id": 10, "id": 10}, {"area": 66681, "iscrowd": 0, "bbox": [185, 495, 239, 279], "category_id": 6, "ignore": 0, "segmentation": [], "image_id": 11, "id": 11}, {"area": 96496, "iscrowd": 0, "bbox": [185, 345, 296, 326], "category_id": 6, "ignore": 0, "segmentation": [], "image_id": 12, "id": 12}, {"area": 70924, "iscrowd": 0, "bbox": [228, 433, 238, 298], "category_id": 6, "ignore": 0, "segmentation": [], "image_id": 13, "id": 13}, {"area": 71036, "iscrowd": 0, "bbox": [233, 530, 236, 301], "category_id": 6, "ignore": 0, "segmentation": [], "image_id": 14, "id": 14}, {"area": 121028, "iscrowd": 0, "bbox": [273, 518, 316, 383], "category_id": 6, "ignore": 0, "segmentation": [], "image_id": 15, "id": 15}, {"area": 37944, "iscrowd": 0, "bbox": [298, 730, 186, 204], "category_id": 5, "ignore": 0, "segmentation": [], "image_id": 16, "id": 16}, {"area": 11448, "iscrowd": 0, "bbox": [283, 698, 106, 108], "category_id": 5, "ignore": 0, "segmentation": [], "image_id": 17, "id": 17}, {"area": 27384, "iscrowd": 0, "bbox": [288, 678, 163, 168], "category_id": 5, "ignore": 0, "segmentation": [], "image_id": 18, "id": 18}, {"area": 33432, "iscrowd": 0, "bbox": [288, 685, 168, 199], "category_id": 5, "ignore": 0, "segmentation": [], "image_id": 19, "id": 19}, {"area": 11211, "iscrowd": 0, "bbox": [335, 775, 101, 111], "category_id": 5, "ignore": 0, "segmentation": [], "image_id": 20, "id": 20}, {"area": 26986, "iscrowd": 0, "bbox": [193, 713, 206, 131], "category_id": 3, "ignore": 0, "segmentation": [], "image_id": 21, "id": 21}, {"area": 21054, "iscrowd": 0, "bbox": [335, 925, 121, 174], "category_id": 3, "ignore": 0, "segmentation": [], "image_id": 22, "id": 22}, {"area": 13056, "iscrowd": 0, "bbox": [255, 788, 136, 96], "category_id": 3, "ignore": 0, "segmentation": [], "image_id": 23, "id": 23}, {"area": 43581, "iscrowd": 0, "bbox": [270, 770, 219, 199], "category_id": 3, "ignore": 0, "segmentation": [], "image_id": 24, "id": 24}, {"area": 27566, "iscrowd": 0, "bbox": [385, 1000, 154, 179], "category_id": 3, "ignore": 0, "segmentation": [], "image_id": 25, "id": 25}, {"area": 42364, "iscrowd": 0, "bbox": [170, 740, 356, 119], "category_id": 7, "ignore": 0, "segmentation": [], "image_id": 26, "id": 26}, {"area": 89804, "iscrowd": 0, "bbox": [175, 740, 314, 286], "category_id": 7, "ignore": 0, "segmentation": [], "image_id": 27, "id": 27}, {"area": 49408, "iscrowd": 0, "bbox": [130, 568, 386, 128], "category_id": 7, "ignore": 0, "segmentation": [], "image_id": 28, "id": 28}, {"area": 44104, "iscrowd": 0, "bbox": [375, 828, 149, 296], "category_id": 7, "ignore": 0, "segmentation": [], "image_id": 29, "id": 29}, {"area": 72009, "iscrowd": 0, "bbox": [235, 688, 189, 381], "category_id": 7, "ignore": 0, "segmentation": [], "image_id": 30, "id": 30}, {"area": 179136, "iscrowd": 0, "bbox": [298, 540, 311, 576], "category_id": 4, "ignore": 0, "segmentation": [], "image_id": 31, "id": 31}, {"area": 194052, "iscrowd": 0, "bbox": [150, 288, 314, 618], "category_id": 4, "ignore": 0, "segmentation": [], "image_id": 32, "id": 32}, {"area": 30856, "iscrowd": 0, "bbox": [178, 608, 116, 266], "category_id": 4, "ignore": 0, "segmentation": [], "image_id": 33, "id": 33}, {"area": 30284, "iscrowd": 0, "bbox": [268, 783, 113, 268], "category_id": 4, "ignore": 0, "segmentation": [], "image_id": 34, "id": 34}, {"area": 65604, "iscrowd": 0, "bbox": [140, 635, 284, 231], "category_id": 4, "ignore": 0, "segmentation": [], "image_id": 35, "id": 35}], "categories": [{"supercategory": "none", "id": 1, "name": "mobile_phone"}, {"supercategory": "none", "id": 2, "name": "scissors"}, {"supercategory": "none", "id": 3, "name": "light_bulb"}, {"supercategory": "none", "id": 4, "name": "tin_can"}, {"supercategory": "none", "id": 5, "name": "ball"}, {"supercategory": "none", "id": 6, "name": "mug"}, {"supercategory": "none", "id": 7, "name": "remote_control"}]}